HISTORY.md
LICENSE
MANIFEST.in
README.md
setup.cfg
setup.py
scieloapi/__init__.py
scieloapi/core.py
scieloapi/exceptions.py
scieloapi/httpbroker.py
scieloapi.egg-info/PKG-INFO
scieloapi.egg-info/SOURCES.txt
scieloapi.egg-info/dependency_links.txt
scieloapi.egg-info/requires.txt
scieloapi.egg-info/top_level.txt