Metadata-Version: 1.0
Name: scieloapi
Version: 0.4
Summary: Thin wrapper around the SciELO Manager RESTful API.
Home-page: http://docs.scielo.org
Author: Gustavo Fonseca
Author-email: gustavo.fonseca@scielo.org
License: BSD License
Platform: UNKNOWN
Classifier: Development Status :: 4 - Beta
Classifier: Intended Audience :: Developers
Classifier: Programming Language :: Python
Classifier: Topic :: Software Development :: Libraries :: Python Modules
